solaredgeha/__init__.py
solaredgeha/solaredgeha.py
solaredgeha-0.3.2.dist-info/METADATA
solaredgeha-0.3.2.dist-info/WHEEL
solaredgeha-0.3.2.dist-info/licenses/LICENSE
solaredgeha-0.3.2.dist-info/RECORD
