Metadata-Version: 2.4
Name: solaredgeha
Version: 0.3.2
Summary: A python API wrapper for Solaredge Home Automation service
Project-URL: Homepage, https://github.com/amccarthy/solaredge-ha
Project-URL: Issues, https://github.com/amccarthy/solaredge-ha/issues
Author-email: Aaron McCarthy <mccarthy.aaron@gmail.com>
License: The MIT License (MIT)
License-File: LICENSE
Keywords: home automation,solaredge
Classifier: Development Status :: 3 - Alpha
Classifier: Intended Audience :: Developers
Classifier: License :: OSI Approved :: MIT License
Classifier: Programming Language :: Python :: 3
Classifier: Programming Language :: Python :: 3.12
Classifier: Topic :: Scientific/Engineering
Requires-Python: >=3.12
Requires-Dist: aiohttp>=3.12.14
Requires-Dist: yarl>=1.20.1
